{
    "headLine": "TST Colloquium",
    "content": {
        "blueBox": {
            "headLine": "Mission",
            "content": [
                "The colloquium of the Chair for Theory of Science and Technology (TST) addresses a variety of topics related to the theory of (computational) science and technology for Master’s and PhD students as well as postdocs. It discusses the literature of the workshops organized by the CSS Lab and hosts the reading group on code studies organized by Dawid Kasprowicz and Jennifer Schaffrath.",
                "The colloquium takes place on Thursdays during the lecture period from 3 to 6 p.m., in case of guest lectures (events) from 4 to 6 p.m. Location: Online via Zoom or CSS Lab (room 410), Theaterplatz 14, RWTH Aachen University. Accreditation is required under: dawid.kasprowicz@humtec.rwth-aachen.de."
            ]
        },
        "box1": {
            "headLine": "Winter Term 2020/2021"
        },
        "box2": {
            "headLine": "Summer Term 2020"
        },
        "box3": {
            "headLine": "Winter Term 2019/2020"
        },
        "box4": {
            "headLine": "Summer Term 2019"
        },
        "box5": {
            "headLine": "Winter Term 2018/2019"
        },
        "box6": {
            "headLine": "Summer Term 2018"
        }
    }
}